whatsbyapi/__init__.py
whatsbyapi/api.py
whatsbyapi/client.py
whatsbyapi/errors.py
whatsbyapi/filters.py
whatsbyapi/handlers.py
whatsbyapi/server.py
whatsbyapi/utils.py
whatsbyapi/types/__init__.py
whatsbyapi/types/base_update.py
whatsbyapi/types/callback.py
whatsbyapi/types/chat_opened.py
whatsbyapi/types/flows.py
whatsbyapi/types/media.py
whatsbyapi/types/message.py
whatsbyapi/types/message_status.py
whatsbyapi/types/others.py
whatsbyapi/types/template.py
whatsbyapi-1.0.0.dist-info/LICENSE
whatsbyapi-1.0.0.dist-info/METADATA
whatsbyapi-1.0.0.dist-info/WHEEL
whatsbyapi-1.0.0.dist-info/top_level.txt
whatsbyapi-1.0.0.dist-info/RECORD
